{
  "$schema": "https://turborepo.org/schema.json",
  "pipeline": {
    "build": {
      "cache": false,
      "outputs": []
    },
    "dev": {
      "cache": false,
      "outputs": [],
      "persistent": true
    },
    "lint": {
      "dependsOn": ["^lint"],
      "outputs": []
    },
    "test": {
      "dependsOn": ["db:generate"],
      "outputs": [],
      "inputs": ["prisma/schema.prisma"]
    },
    "db:generate": {
      "cache": false,
      "outputs": []
    },
    "db:migrate": {
      "cache": false,
      "outputs": [],
      "inputs": ["prisma/schema.prisma"]
    },
    "db:seed": {
      "cache": false,
      "outputs": []
    },
    "docker": {
      "cache": false,
      "dependsOn": ["^docker"],
      "outputs": [],
      "persistent": true
    },
    "docker:build": {
      "cache": false,
      "outputs": []
    }
  }
}
